slvrov_tools/__init__.py
slvrov_tools/camera_tools.py
slvrov_tools/gst_udp_cam.py
slvrov_tools/i2c_device.py
slvrov_tools/joystick.py
slvrov_tools/legacy_pca9685.py
slvrov_tools/math_tools.py
slvrov_tools/misc_tools.py
slvrov_tools/network_tools.py
slvrov_tools/pca9685.py
slvrov_tools/set_ip.py
slvrov_tools-0.1.19.dist-info/licenses/LICENSE
slvrov_tools-0.1.19.dist-info/METADATA
slvrov_tools-0.1.19.dist-info/WHEEL
slvrov_tools-0.1.19.dist-info/entry_points.txt
slvrov_tools-0.1.19.dist-info/top_level.txt
slvrov_tools-0.1.19.dist-info/RECORD
