Metadata-Version: 2.4
Name: slvrov-tools
Version: 0.1.19
Summary: Tools for math, networking, joysticks, I2C devices, and more for use in SLVROV.
Author-email: Caleb Hofschneider <calebhof11@gmail.com>
License: MIT
Requires-Python: >=3.7
License-File: LICENSE
Requires-Dist: smbus2>=0.4.1; sys_platform == "linux"
Requires-Dist: PySDL2>=0.9.7
Requires-Dist: opencv-python>=4.12
Dynamic: license-file
